edc_document_status/__init__.py
edc_document_status/apps.py
edc_document_status/fieldsets.py
edc_document_status/model_mixins.py
edc_document_status/modeladmin_mixins.py
edc_document_status/urls.py
edc_document_status/models/__init__.py
edc_document_status/models/signals.py
edc_document_status/tests/__init__.py
edc_document_status/tests/test_settings.py
edc_document_status/tests/etc/user-aes-local.key
edc_document_status/tests/etc/user-aes-restricted.key
edc_document_status/tests/etc/user-rsa-local-private.pem
edc_document_status/tests/etc/user-rsa-local-public.pem
edc_document_status/tests/etc/user-rsa-restricted-private.pem
edc_document_status/tests/etc/user-rsa-restricted-public.pem
edc_document_status/tests/etc/user-salt-local.key
edc_document_status/tests/etc/user-salt-restricted.key
edc_document_status/tests/tests/__init__.py
edc_document_status-1.0.0.dist-info/AUTHORS
edc_document_status-1.0.0.dist-info/LICENSE
edc_document_status-1.0.0.dist-info/METADATA
edc_document_status-1.0.0.dist-info/WHEEL
edc_document_status-1.0.0.dist-info/top_level.txt
edc_document_status-1.0.0.dist-info/RECORD
